eggviron/__init__.py
eggviron/_awsparamstore_loader.py
eggviron/_eggviron.py
eggviron/_envfile_loader.py
eggviron/_environ_loader.py
eggviron/py.typed
eggviron-1.1.0.dist-info/METADATA
eggviron-1.1.0.dist-info/WHEEL
eggviron-1.1.0.dist-info/licenses/LICENSE
eggviron-1.1.0.dist-info/RECORD
