Metadata-Version: 2.4
Name: eggviron
Version: 1.1.0
Summary: A library for loading and accessing environment variable values from various sources.
Project-URL: homepage, https://github.com/Preocts/eggviron
Author-email: Preocts <preocts@preocts.com>
License-Expression: MIT
License-File: LICENSE
Classifier: Programming Language :: Python :: 3
Classifier: Programming Language :: Python :: 3 :: Only
Classifier: Programming Language :: Python :: Implementation :: CPython
Requires-Python: <3.15,>=3.10
Provides-Extra: aws
Requires-Dist: boto3>=v1.40.7; extra == 'aws'
